genai_session/__init__.py
genai_session/session.py
genai_session/utils/__init__.py
genai_session/utils/agents.py
genai_session/utils/context.py
genai_session/utils/exceptions.py
genai_session/utils/file_manager.py
genai_session/utils/function_annotation.py
genai_session/utils/logging_manager.py
genai_session/utils/naming_enums.py
genai_protocol-2.0.3.dist-info/LICENSE
genai_protocol-2.0.3.dist-info/METADATA
genai_protocol-2.0.3.dist-info/WHEEL
genai_protocol-2.0.3.dist-info/top_level.txt
genai_protocol-2.0.3.dist-info/RECORD
