Metadata-Version: 2.2
Name: genai-protocol
Version: 2.0.3
Summary: A universal agents connector library that integrates with GenAI.works infrastructure
Home-page: https://github.com/genai-works-org/genai-protocol
Author: Yaroslav Oliinyk, Valentyn Slivko, Ivan Kuzlo, Pavlo Shyrinskykh
Author-email: pavlo.shyrinskykh@genai.works
License: Apache License 2.0
Classifier: Programming Language :: Python :: 3.10
Classifier: Programming Language :: Python :: 3.11
Classifier: Programming Language :: Python :: 3.12
Classifier: License :: OSI Approved :: Apache Software License
Classifier: Operating System :: OS Independent
Requires-Python: >=3.10
License-File: LICENSE
Requires-Dist: aiohappyeyeballs>=2.6.1
Requires-Dist: aiohttp>=3.11.16
Requires-Dist: aiosignal>=1.3.2
Requires-Dist: annotated-types>=0.7.0
Requires-Dist: attrs>=25.3.0
Requires-Dist: frozenlist>=1.5.0
Requires-Dist: idna>=3.10
Requires-Dist: multidict>=6.2.0
Requires-Dist: propcache>=0.3.1
Requires-Dist: pydantic>=2.11.1
Requires-Dist: pydantic-core>=2.33.0
Requires-Dist: typing-extensions>=4.13.0
Requires-Dist: typing-inspection>=0.4.0
Requires-Dist: websockets>=15.0.1
Requires-Dist: yarl>=1.18.3
Requires-Dist: pyjwt>=2.10.1
Requires-Dist: python-dotenv>=1.1.1
Provides-Extra: dev
Requires-Dist: twine>=6.1.0; extra == "dev"
Dynamic: author
Dynamic: author-email
Dynamic: classifier
Dynamic: description
Dynamic: description-content-type
Dynamic: home-page
Dynamic: license
Dynamic: provides-extra
Dynamic: requires-dist
Dynamic: requires-python
Dynamic: summary
